{
    "device": {
        "id": "device_1",
        "is_active": true,
        "is_private_session": false,
        "is_restricted": false,
        "name": "Test Device",
        "type": "computer",
        "volume_percent": 75,
        "supports_volume": true
    },
    "repeat_state": "off",
    "shuffle_state": false,
    "context": {
        "type": "playlist",
        "href": "https://api.spotify.com/v1/playlists/playlist_1",
        "external_urls": {
            "spotify": "https://open.spotify.com/playlist/playlist_1"
        },
        "uri": "spotify:playlist:playlist_1"
    },
    "timestamp": 1700000000000,
    "progress_ms": 30000,
    "is_playing": true,
    "currently_playing_type": "track",
    "actions": {
        "pausing": true,
        "resuming": false,
        "skipping_next": true,
        "skipping_prev": true
    },
    "item": {
        "id": "track_1",
        "name": "Test Track",
        "duration_ms": 180000,
        "explicit": false,
        "uri": "spotify:track:track_1",
        "href": "https://api.spotify.com/v1/tracks/track_1",
        "type": "track",
        "disc_number": 1,
        "track_number": 1,
        "popularity": 75,
        "is_local": false,
        "external_ids": {
            "isrc": "USTEST123"
        },
        "external_urls": {
            "spotify": "https://open.spotify.com/track/track_1"
        },
        "artists": [
            {
                "id": "artist_1",
                "name": "Test Artist",
                "type": "artist",
                "href": "https://api.spotify.com/v1/artists/artist_1",
                "uri": "spotify:artist:artist_1",
                "external_urls": {
                    "spotify": "https://open.spotify.com/artist/artist_1"
                }
            }
        ],
        "album": {
            "id": "album_1",
            "name": "Test Album",
            "href": "https://api.spotify.com/v1/albums/album_1",
            "uri": "spotify:album:album_1",
            "images": [],
            "external_urls": {
                "spotify": "https://open.spotify.com/album/album_1"
            },
            "album_type": "album",
            "total_tracks": 12,
            "available_markets": ["US"],
            "release_date": "2024-01-01",
            "release_date_precision": "day",
            "type": "album",
            "artists": [
                {
                    "id": "artist_1",
                    "name": "Test Artist",
                    "href": "https://api.spotify.com/v1/artists/artist_1",
                    "uri": "spotify:artist:artist_1",
                    "type": "artist",
                    "external_urls": {
                        "spotify": "https://open.spotify.com/artist/artist_1"
                    }
                }
            ]
        }
    }
}
